README.rst
setup.py
salt_broker.egg-info/PKG-INFO
salt_broker.egg-info/SOURCES.txt
salt_broker.egg-info/dependency_links.txt
salt_broker.egg-info/requires.txt
salt_broker.egg-info/top_level.txt
saltbroker/__init__.py
saltbroker/broker.py
saltbroker/config.py
saltbroker/metadata.py
saltbroker/scripts.py
saltbroker/utils/__init__.py
saltbroker/utils/parsers.py
saltbroker/utils/zeromq.py
scripts/salt-broker