Metadata-Version: 1.0
Name: salt-broker
Version: 0.2.5
Summary: A lightweight proxy for saltstack
Home-page: https://github.com/pengyao/salt-broker
Author: pengyao
Author-email: pengyao@pengyao.org
License: Apache License V2.0
Platform: UNKNOWN
